emmnesia/EMM.py
emmnesia/__init__.py
emmnesia/definitions.py
emmnesia/pandas_utils.py
emmnesia/utils.py
tests/__init__.py
tests/test_queues.py
emmnesia-0.1.2.dist-info/LICENSE
emmnesia-0.1.2.dist-info/METADATA
emmnesia-0.1.2.dist-info/WHEEL
emmnesia-0.1.2.dist-info/top_level.txt
emmnesia-0.1.2.dist-info/RECORD
