Metadata-Version: 2.1
Name: emmnesia
Version: 0.1.2
Summary: Exceptional Model Mining (EMM)
Home-page: https://github.com/zbenmo/emmnesia
Author: Oren Zeev-Ben-Mordehai
Author-email: zbenmo@gmail.com
Maintainer: zbenmo@gmail.com
License: Apache License
Classifier: Intended Audience :: Developers
Classifier: Intended Audience :: Science/Research
Classifier: Programming Language :: Python :: 3
Classifier: Programming Language :: Python :: 3.7
Classifier: Programming Language :: Python :: 3.8
Classifier: Programming Language :: Python :: 3.9
Classifier: License :: OSI Approved :: MIT License
Classifier: Topic :: Scientific/Engineering
Classifier: Topic :: Scientific/Engineering :: Artificial Intelligence
License-File: LICENSE
Requires-Dist: pandas (<1.6,>=1.5.2)
Requires-Dist: numpy (<1.24,>=1.23.5)
Provides-Extra: examples
Requires-Dist: scikit-learn (<1.2,>=1.1.3) ; extra == 'examples'
Provides-Extra: tests
Requires-Dist: pytest ; extra == 'tests'
